<annotation>
	<folder>train</folder>
	<filename>Meals_81.jpg</filename>
	<path>G:\Meals\train\Meals_81.jpg</path>
	<source>
		<database>Unknown</database>
	</source>
	<size>
		<width>3024</width>
		<height>4032</height>
		<depth>3</depth>
	</size>
	<segmented>0</segmented>
	<object>
		<name>vegetables</name>
		<pose>Unspecified</pose>
		<truncated>0</truncated>
		<difficult>0</difficult>
		<bndbox>
			<xmin>659</xmin>
			<ymin>2787</ymin>
			<xmax>1502</xmax>
			<ymax>3500</ymax>
		</bndbox>
	</object>
	<object>
		<name>rice</name>
		<pose>Unspecified</pose>
		<truncated>0</truncated>
		<difficult>0</difficult>
		<bndbox>
			<xmin>9</xmin>
			<ymin>2675</ymin>
			<xmax>609</xmax>
			<ymax>3612</ymax>
		</bndbox>
	</object>
	<object>
		<name>meat</name>
		<pose>Unspecified</pose>
		<truncated>0</truncated>
		<difficult>0</difficult>
		<bndbox>
			<xmin>559</xmin>
			<ymin>2300</ymin>
			<xmax>1427</xmax>
			<ymax>2762</ymax>
		</bndbox>
	</object>
	<object>
		<name>rice</name>
		<pose>Unspecified</pose>
		<truncated>0</truncated>
		<difficult>0</difficult>
		<bndbox>
			<xmin>1671</xmin>
			<ymin>393</ymin>
			<xmax>2021</xmax>
			<ymax>656</ymax>
		</bndbox>
	</object>
	<object>
		<name>vegetables</name>
		<pose>Unspecified</pose>
		<truncated>0</truncated>
		<difficult>0</difficult>
		<bndbox>
			<xmin>1040</xmin>
			<ymin>175</ymin>
			<xmax>1627</xmax>
			<ymax>606</ymax>
		</bndbox>
	</object>
</annotation>
