<annotation>
	<folder>train</folder>
	<filename>Meals_252.jpg</filename>
	<path>G:\Meals\train\Meals_252.jpg</path>
	<source>
		<database>Unknown</database>
	</source>
	<size>
		<width>3024</width>
		<height>1153</height>
		<depth>3</depth>
	</size>
	<segmented>0</segmented>
	<object>
		<name>rice</name>
		<pose>Unspecified</pose>
		<truncated>0</truncated>
		<difficult>0</difficult>
		<bndbox>
			<xmin>1346</xmin>
			<ymin>507</ymin>
			<xmax>1598</xmax>
			<ymax>601</ymax>
		</bndbox>
	</object>
	<object>
		<name>vegetables</name>
		<pose>Unspecified</pose>
		<truncated>0</truncated>
		<difficult>0</difficult>
		<bndbox>
			<xmin>1174</xmin>
			<ymin>423</ymin>
			<xmax>1464</xmax>
			<ymax>495</ymax>
		</bndbox>
	</object>
	<object>
		<name>meat</name>
		<pose>Unspecified</pose>
		<truncated>0</truncated>
		<difficult>0</difficult>
		<bndbox>
			<xmin>999</xmin>
			<ymin>535</ymin>
			<xmax>1240</xmax>
			<ymax>701</ymax>
		</bndbox>
	</object>
</annotation>
