<annotation>
	<folder>train</folder>
	<filename>Meals_69.jpg</filename>
	<path>G:\Meals\train\Meals_69.jpg</path>
	<source>
		<database>Unknown</database>
	</source>
	<size>
		<width>3024</width>
		<height>1608</height>
		<depth>3</depth>
	</size>
	<segmented>0</segmented>
	<object>
		<name>vegetables</name>
		<pose>Unspecified</pose>
		<truncated>0</truncated>
		<difficult>0</difficult>
		<bndbox>
			<xmin>1083</xmin>
			<ymin>749</ymin>
			<xmax>1853</xmax>
			<ymax>1267</ymax>
		</bndbox>
	</object>
	<object>
		<name>meat</name>
		<pose>Unspecified</pose>
		<truncated>0</truncated>
		<difficult>0</difficult>
		<bndbox>
			<xmin>1570</xmin>
			<ymin>428</ymin>
			<xmax>2118</xmax>
			<ymax>867</ymax>
		</bndbox>
	</object>
</annotation>
